jsonschema2ddl/__init__.py
jsonschema2ddl/models.py
jsonschema2ddl/translators.py
jsonschema2ddl/types.py
jsonschema2ddl/utils.py
jsonschema2ddl-0.3.0.dist-info/LICENSE
jsonschema2ddl-0.3.0.dist-info/WHEEL
jsonschema2ddl-0.3.0.dist-info/METADATA
jsonschema2ddl-0.3.0.dist-info/RECORD
