Metadata-Version: 2.1
Name: jsonschema2ddl
Version: 0.3.0
Summary: Generate Database tables from JSON schema
Author: Pablo San José
Author-email: pablo.sanjose@clarity.ai
Requires-Python: >=3.7,<4.0
Classifier: Programming Language :: Python :: 3
Classifier: Programming Language :: Python :: 3.7
Classifier: Programming Language :: Python :: 3.8
Classifier: Programming Language :: Python :: 3.9
Requires-Dist: change_case (>=0.5.2,<0.6.0)
Requires-Dist: iso8601 (>=0.1.12,<0.2.0)
Requires-Dist: jsonschema (>=3.2.0,<4.0.0)
